<Ui xmlns="http://www.blizzard.com/wow/ui/">
	<Script file ="AddonManager.lua"/>
	<Script file='AutoLFG.lua'/>
	<Script file ="CloseUp.lua"/>
	<Script file ="Disenchanting.lua"/>
	<Script file ="FastError.lua"/>
	<Script file ="Glow.lua"/>
	<Script file='memory.lua'/>
	<Script file ="MiniMapPanels.lua"/>
	<Script file ="Molinari.lua"/>
	<Script file ="PVPx_off.lua"/>
	<Script file ="sMirrorBars.lua"/>
	<Script file ="tekKompare.lua"/>
	<Script file ="TooltipItemIcon.lua"/>
	<Script file ="TradeTab.lua"/>
	
</Ui>